gaccode_monitor-0.1.2.dist-info/licenses/LICENSE
py/__init__.py
py/fetch_gaccode_balance.py
py/gaccode_tray_icon.py
py/utils/__init__.py
py/utils/constants.py
py/utils/log_util.py
py/utils/unique_id_generator.py
gaccode_monitor-0.1.2.dist-info/METADATA
gaccode_monitor-0.1.2.dist-info/WHEEL
gaccode_monitor-0.1.2.dist-info/entry_points.txt
gaccode_monitor-0.1.2.dist-info/top_level.txt
gaccode_monitor-0.1.2.dist-info/RECORD
