Metadata-Version: 2.4
Name: gaccode-monitor
Version: 0.1.2
Summary: A system tray application to monitor GACCode credits balance
Home-page: https://github.com/yourusername/watchGacCredits
Author: GACCode Monitor Team
Author-email: hujiawei34 <huandrong@163.com>
License: MIT
Project-URL: Homepage, https://github.com/hujiawei34/watchGacCredits
Project-URL: Bug Tracker, https://github.com/hujiawei34/watchGacCredits/issues
Classifier: Programming Language :: Python :: 3
Classifier: License :: OSI Approved :: MIT License
Classifier: Operating System :: Microsoft :: Windows
Requires-Python: >=3.6
License-File: LICENSE
Requires-Dist: requests
Requires-Dist: schedule
Requires-Dist: pystray
Requires-Dist: pillow
Dynamic: author
Dynamic: home-page
Dynamic: license-file
Dynamic: requires-python
